{
  "hash": "e1a68e2eb0a7d7725e160223331c0eb5",
  "result": {
    "markdown": "---\ntitle: \"Cool Slides\"\nauthor: \"First Last\"\nformat: \n  revealjs:\n    slide-number: true\n    show-slide-number: print\n    footer: \"[Return to Home Page](..)\"\n    theme: custom.scss\n---\n\n\n\n\n\n## Data `storms`\n\n\n::: {.cell}\n::: {.cell-output .cell-output-stdout}\n```\n# A tibble: 19,066 × 13\n   name   year month   day  hour   lat  long status      category  wind pressure\n   <chr> <dbl> <dbl> <int> <dbl> <dbl> <dbl> <fct>          <dbl> <int>    <int>\n 1 Amy    1975     6    27     0  27.5 -79   tropical d…       NA    25     1013\n 2 Amy    1975     6    27     6  28.5 -79   tropical d…       NA    25     1013\n 3 Amy    1975     6    27    12  29.5 -79   tropical d…       NA    25     1013\n 4 Amy    1975     6    27    18  30.5 -79   tropical d…       NA    25     1013\n 5 Amy    1975     6    28     0  31.5 -78.8 tropical d…       NA    25     1012\n 6 Amy    1975     6    28     6  32.4 -78.7 tropical d…       NA    25     1012\n 7 Amy    1975     6    28    12  33.3 -78   tropical d…       NA    25     1011\n 8 Amy    1975     6    28    18  34   -77   tropical d…       NA    30     1006\n 9 Amy    1975     6    29     0  34.4 -75.8 tropical s…       NA    35     1004\n10 Amy    1975     6    29     6  34   -74.8 tropical s…       NA    40     1002\n# ℹ 19,056 more rows\n# ℹ 2 more variables: tropicalstorm_force_diameter <int>,\n#   hurricane_force_diameter <int>\n```\n:::\n:::\n\n\n\n# Plotting Storms in 1975\n\n\n## Plot storms' paths (example 1)\n\n\n::: {.cell}\n\n```{.r .cell-code  code-fold=\"true\" code-summary=\"View Plot Code\"}\nstorms |>\n  filter(year == 1975) |>\n  ggplot(aes(x = long, y = lat, group = name)) +\n  geom_point() +\n  geom_path() + \n  labs(title = \"North Atlantic Storms (1975)\")\n```\n\n::: {.cell-output-display}\n![](slides-abc_files/figure-revealjs/unnamed-chunk-3-1.png){width=960}\n:::\n:::\n\n\n\n## Plot storms' paths (example 2)\n\n\n::: {.cell}\n\n```{.r .cell-code  code-fold=\"true\" code-summary=\"View Plot Code\"}\nstorms |>\n  filter(year == 1975) |>\n  ggplot(aes(x = long, y = lat, group = name, color = name)) +\n  geom_point(size = 1) +\n  geom_path(arrow = arrow(length = unit(0.1, \"inches\"))) + \n  labs(title = \"North Atlantic Storms (1975)\")\n```\n\n::: {.cell-output-display}\n![](slides-abc_files/figure-revealjs/unnamed-chunk-4-1.png){width=960}\n:::\n:::\n\n\n\n## Plot storms' paths (example 3)\n\n\n::: {.cell}\n\n```{.r .cell-code  code-fold=\"true\" code-summary=\"View Plot Code\"}\nstorms |>\n  filter(year == 1975) |>\n  ggplot(aes(x = long, y = lat, group = name, color = name)) +\n  geom_point(size = 0.5, alpha = 0.5) +\n  geom_path(arrow = arrow(length = unit(0.1, \"inches\"))) + \n  facet_wrap(~ month) +\n  labs(title = \"North Atlantic Storms (1975)\") +\n  theme_bw()\n```\n\n::: {.cell-output-display}\n![](slides-abc_files/figure-revealjs/unnamed-chunk-5-1.png){width=960}\n:::\n:::\n\n\n\n# Maps\n\n\n## Wouldn't this be nice?\n\n\n::: {.cell}\n::: {.cell-output-display}\n![](slides-abc_files/figure-revealjs/map1-1.png){width=960}\n:::\n:::\n\n\n\n## Code\n\n\n::: {.cell}\n\n```{.r .cell-code}\nworld_countries = ne_countries(returnclass = \"sf\")\n\nstorms75 = storms |> filter(year == 1975)\n\nggplot() +\n  geom_sf(data = world_countries) +\n  coord_sf(xlim = c(-110, 0), ylim = c(5, 65)) +\n  geom_point(data = storms75, \n          aes(x = long, y = lat, group = name, color = name),\n          size = 0.5, alpha = 0.5) +\n  geom_path(data = storms75, \n          aes(x = long, y = lat, group = name, color = name),\n          arrow = arrow(length = unit(0.1, \"inches\"))) + \n  theme(panel.background = element_blank(),\n        axis.ticks = element_blank(), # hide tick marks\n        axis.text = element_blank()) + # hide degree values of lat & lon\n  labs(title = \"North Atlantic Storms (1975)\",\n       x = \"\", \n       y = \"\")\n```\n:::\n",
    "supporting": [
      "slides-abc_files"
    ],
    "filters": [
      "rmarkdown/pagebreak.lua"
    ],
    "includes": {
      "include-after-body": [
        "\n<script>\n  // htmlwidgets need to know to resize themselves when slides are shown/hidden.\n  // Fire the \"slideenter\" event (handled by htmlwidgets.js) when the current\n  // slide changes (different for each slide format).\n  (function () {\n    function fireSlideChanged(previousSlide, currentSlide) {\n\n      // dispatch for htmlwidgets\n      const event = window.document.createEvent(\"Event\");\n      event.initEvent(\"slideenter\", true, true);\n      window.document.dispatchEvent(event);\n\n      // dispatch for shiny\n      if (window.jQuery) {\n        if (previousSlide) {\n          window.jQuery(previousSlide).trigger(\"hidden\");\n        }\n        if (currentSlide) {\n          window.jQuery(currentSlide).trigger(\"shown\");\n        }\n      }\n    }\n\n    // hookup for reveal\n    if (window.Reveal) {\n      window.Reveal.addEventListener(\"slidechanged\", function(event) {\n        fireSlideChanged(event.previousSlide, event.currentSlide);\n      });\n    }\n\n    // hookup for slidy\n    if (window.w3c_slidy) {\n      window.w3c_slidy.add_observer(function (slide_num) {\n        // slide_num starts at position 1\n        fireSlideChanged(null, w3c_slidy.slides[slide_num - 1]);\n      });\n    }\n\n  })();\n</script>\n\n"
      ]
    },
    "engineDependencies": {},
    "preserve": {},
    "postProcess": true
  }
}